PySimpleAES/__init__.py
PySimpleAES-0.0.2.dist-info/DESCRIPTION.rst
PySimpleAES-0.0.2.dist-info/METADATA
PySimpleAES-0.0.2.dist-info/RECORD
PySimpleAES-0.0.2.dist-info/WHEEL
PySimpleAES-0.0.2.dist-info/metadata.json
PySimpleAES-0.0.2.dist-info/top_level.txt
