Metadata-Version: 2.0
Name: PySimpleAES
Version: 0.0.2
Summary: Python AES encryptation
Home-page: https://github.com/FRReinert/AES
Author: Fabricio Roberto reinert
Author-email: fabricio.reinert@live.com
License: MIT license
Keywords: Python,AES,cryptography
Platform: UNKNOWN
Classifier: Development Status :: 2 - Pre-Alpha
Classifier: Intended Audience :: Developers
Classifier: License :: OSI Approved :: MIT License
Classifier: Natural Language :: English
Classifier: Programming Language :: Python :: 3.6
Requires-Dist: cryptography
